mypackage_davidattiah/__init__.py
mypackage_davidattiah/decorators.py
mypackage_davidattiah/descriptors.py
mypackage_davidattiah/generators.py
mypackage_davidattiah/iterators.py
mypackage_davidattiah-0.1.dist-info/METADATA
mypackage_davidattiah-0.1.dist-info/WHEEL
mypackage_davidattiah-0.1.dist-info/top_level.txt
mypackage_davidattiah-0.1.dist-info/RECORD
