Metadata-Version: 2.1
Name: mypackage_davidattiah
Version: 0.1
Summary: A package sample with generators, iterators, decorators, and descriptors
Home-page: https://github.com/david-attiah/mypackage_davidattiah
Author: David Attiah
Author-email: davidkumah@gmail.com
Classifier: Programming Language :: Python :: 3
Classifier: License :: OSI Approved :: MIT License
Classifier: Operating System :: OS Independent
Requires-Python: >=3.6
